MANIFEST.in
reconfig.py
setup.py
reconfig.egg-info/PKG-INFO
reconfig.egg-info/SOURCES.txt
reconfig.egg-info/dependency_links.txt
reconfig.egg-info/requires.txt
reconfig.egg-info/top_level.txt