Metadata-Version: 1.1
Name: reconfig
Version: 0.0.1
Summary: YAML config file manager with signal-triggered reloading and watchable key/value changes
Home-page: http://github.com/teepark/reconfig
Author: Travis Parker
Author-email: travis.parker@gmail.com
License: BSD
Platform: UNKNOWN
Classifier: Development Status :: 3 - Alpha
Classifier: Intended Audience :: Developers
Classifier: License :: OSI Approved :: BSD License
Classifier: Natural Language :: English
Classifier: Programming Language :: Python
